SpeakerCraft
